unravel/__init__.py
unravel/analysis.py
unravel/core.py
unravel/example.py
unravel/stream.py
unravel/utils.py
unravel/viz.py
unravel_python-1.6.6.dist-info/licenses/LICENSE
unravel_python-1.6.6.dist-info/METADATA
unravel_python-1.6.6.dist-info/WHEEL
unravel_python-1.6.6.dist-info/top_level.txt
unravel_python-1.6.6.dist-info/RECORD
