Metadata-Version: 2.4
Name: unravel-python
Version: 1.6.6
Summary: Implementation of UNRAVEL
Author-email: Nicolas Delinte <nicolas.delinte@uclouvain.be>
License-Expression: GPL-3.0-only
Project-URL: GitHub, https://github.com/DelinteNicolas/UNRAVEL
Project-URL: Documentation, https://unravel.readthedocs.io/en/latest/
Keywords: tractography,multi-fixel
Classifier: Intended Audience :: Science/Research
Classifier: Natural Language :: English
Classifier: Programming Language :: Python
License-File: LICENSE
Requires-Dist: dipy
Requires-Dist: scikit-image
Requires-Dist: scikit-learn
Provides-Extra: viz
Requires-Dist: pyvista; extra == "viz"
Dynamic: license-file
